{
    "os": "Linux-5.15.0-58-generic-x86_64-with-glibc2.31",
    "python": "3.9.15",
    "heartbeatAt": "2023-02-07T23:27:23.209943",
    "startedAt": "2023-02-07T23:27:16.058957",
    "docker": null,
    "cuda": null,
    "args": [
        "traingnn",
        "-f",
        "./example/traingnn.json"
    ],
    "state": "running",
    "program": "-m dfpl.__main__",
    "git": {
        "remote": "https://git.ufz.de/deepfplearn/deepfplearn_exai.git",
        "commit": "8410c5e4a53bf5b1e9f4aea3303a5c76efe0239d"
    },
    "email": "kyriakos.soulios@ufz.de",
    "root": "/home/soulios/git-soulios/deepFPlearn",
    "host": "ufz542459",
    "username": "soulios",
    "executable": "/home/soulios/anaconda3/envs/dfpl_env/bin/python",
    "cpu_count": 4,
    "cpu_count_logical": 8,
    "cpu_freq": {
        "current": 3405.618,
        "min": 400.0,
        "max": 4900.0
    },
    "cpu_freq_per_core": [
        {
            "current": 3622.098,
            "min": 400.0,
            "max": 4900.0
        },
        {
            "current": 2300.0,
            "min": 400.0,
            "max": 4900.0
        },
        {
            "current": 3523.258,
            "min": 400.0,
            "max": 4900.0
        },
        {
            "current": 3399.009,
            "min": 400.0,
            "max": 4900.0
        },
        {
            "current": 3506.058,
            "min": 400.0,
            "max": 4900.0
        },
        {
            "current": 3183.052,
            "min": 400.0,
            "max": 4900.0
        },
        {
            "current": 3389.067,
            "min": 400.0,
            "max": 4900.0
        },
        {
            "current": 2300.0,
            "min": 400.0,
            "max": 4900.0
        }
    ],
    "disk": {
        "total": 214.24963760375977,
        "used": 188.09548950195312
    },
    "memory": {
        "total": 15.296627044677734
    }
}
